mcha/__init__.py
mcha/models/LLaMA_3.py
mcha/models/__init__.py
mcha/models/base.py
mcha/utils/__init__.py
mcha/utils/constant.py
mcha/utils/entity.py
mcha/utils/io.py
mcha/utils/logger.py
mcha/utils/metrics.py
mcha/utils/rand.py
mcha-0.2.0.dist-info/METADATA
mcha-0.2.0.dist-info/WHEEL
mcha-0.2.0.dist-info/top_level.txt
mcha-0.2.0.dist-info/RECORD
